{"width":512,"SubTexture":[{"y":219,"frameWidth":204,"x":211,"frameHeight":287,"width":94,"frameY":-6,"height":133,"name":"chr_unit_300601-attack_01.png","frameX":-22},{"y":1,"frameWidth":204,"x":327,"frameHeight":287,"width":104,"frameY":-34,"height":132,"name":"chr_unit_300601-attack_00.png","frameX":-54},{"y":224,"frameWidth":204,"x":100,"frameHeight":287,"width":95,"frameY":-138,"height":131,"name":"chr_unit_300601-attack_05.png","frameX":-88},{"y":270,"frameWidth":204,"x":401,"frameHeight":287,"width":92,"frameY":-136,"height":131,"name":"chr_unit_300601-attack_06.png","frameX":-91},{"y":222,"frameWidth":204,"x":1,"frameHeight":287,"width":97,"frameY":-5,"height":129,"name":"chr_unit_300601-attack_02.png","frameX":-8},{"y":583,"frameWidth":204,"x":1,"frameHeight":287,"width":89,"frameY":-135,"height":130,"name":"chr_unit_300601-attack_07.png","frameX":-93},{"y":354,"frameWidth":204,"x":197,"frameHeight":287,"width":103,"frameY":-84,"height":87,"name":"chr_unit_300601-attack_11.png","frameX":-6},{"y":552,"frameWidth":204,"x":167,"frameHeight":287,"width":163,"frameY":-142,"height":71,"name":"chr_unit_300601-attack_14.png","frameX":0},{"y":436,"frameWidth":204,"x":1,"frameHeight":287,"width":164,"frameY":-144,"height":72,"name":"chr_unit_300601-attack_12.png","frameX":0},{"y":135,"frameWidth":204,"x":372,"frameHeight":287,"width":94,"frameY":-131,"height":133,"name":"chr_unit_300601-attack_09.png","frameX":-84},{"y":479,"frameWidth":204,"x":333,"frameHeight":287,"width":163,"frameY":-144,"height":71,"name":"chr_unit_300601-attack_13.png","frameX":0},{"y":270,"frameWidth":204,"x":307,"frameHeight":287,"width":92,"frameY":-134,"height":132,"name":"chr_unit_300601-attack_08.png","frameX":-92},{"y":624,"frameWidth":204,"x":332,"frameHeight":287,"width":82,"frameY":-32,"height":135,"name":"chr_unit_300601-attack_10.png","frameX":-37},{"y":90,"frameWidth":204,"x":109,"frameHeight":287,"width":100,"frameY":-139,"height":132,"name":"chr_unit_300601-attack_04.png","frameX":-84},{"y":89,"frameWidth":204,"x":1,"frameHeight":287,"width":106,"frameY":-45,"height":131,"name":"chr_unit_300601-attack_03.png","frameX":-94},{"y":1,"frameWidth":71,"x":433,"frameHeight":111,"width":70,"frameY":0,"height":110,"name":"chr_unit_300601-damage_0.png","frameX":0},{"y":479,"frameWidth":173,"x":167,"frameHeight":94,"width":164,"frameY":-23,"height":71,"name":"chr_unit_300601-move_10.png","frameX":-8},{"y":625,"frameWidth":173,"x":92,"frameHeight":94,"width":167,"frameY":-24,"height":66,"name":"chr_unit_300601-move_01.png","frameX":-5},{"y":1,"frameWidth":173,"x":1,"frameHeight":94,"width":162,"frameY":-1,"height":86,"name":"chr_unit_300601-move_05.png","frameX":-10},{"y":357,"frameWidth":173,"x":1,"frameHeight":94,"width":161,"frameY":-15,"height":77,"name":"chr_unit_300601-move_08.png","frameX":-11},{"y":1,"frameWidth":173,"x":165,"frameHeight":94,"width":160,"frameY":-1,"height":87,"name":"chr_unit_300601-move_06.png","frameX":-12},{"y":693,"frameWidth":173,"x":92,"frameHeight":94,"width":170,"frameY":-25,"height":63,"name":"chr_unit_300601-move_02.png","frameX":-2},{"y":552,"frameWidth":173,"x":332,"frameHeight":94,"width":163,"frameY":-23,"height":70,"name":"chr_unit_300601-move_09.png","frameX":-9},{"y":510,"frameWidth":173,"x":1,"frameHeight":94,"width":164,"frameY":-23,"height":71,"name":"chr_unit_300601-move_00.png","frameX":-8},{"y":135,"frameWidth":173,"x":211,"frameHeight":94,"width":159,"frameY":-8,"height":82,"name":"chr_unit_300601-move_07.png","frameX":-13},{"y":758,"frameWidth":173,"x":1,"frameHeight":94,"width":172,"frameY":-24,"height":62,"name":"chr_unit_300601-move_03.png","frameX":0},{"y":404,"frameWidth":173,"x":307,"frameHeight":94,"width":165,"frameY":-12,"height":73,"name":"chr_unit_300601-move_04.png","frameX":-7}],"height":1024,"name":"chr_unit_300601","imagePath":"chr_unit_300601_tex.png"}